lb_pidsim_train/__init__.py
lb_pidsim_train/version.py
lb_pidsim_train/algorithms/__init__.py
lb_pidsim_train/algorithms/gan/BceGAN.py
lb_pidsim_train/algorithms/gan/CramerGAN.py
lb_pidsim_train/algorithms/gan/GAN.py
lb_pidsim_train/algorithms/gan/WGAN_ALP.py
lb_pidsim_train/algorithms/gan/WGAN_GP.py
lb_pidsim_train/algorithms/gan/__init__.py
lb_pidsim_train/algorithms/norm_flow/LbVAE.py
lb_pidsim_train/algorithms/norm_flow/NormFlow.py
lb_pidsim_train/algorithms/norm_flow/VAE_NF.py
lb_pidsim_train/algorithms/norm_flow/__init__.py
lb_pidsim_train/callbacks/HopaasReporter.py
lb_pidsim_train/callbacks/__init__.py
lb_pidsim_train/callbacks/gan/HopaasModelSaver.py
lb_pidsim_train/callbacks/gan/ModelSaver.py
lb_pidsim_train/callbacks/gan/__init__.py
lb_pidsim_train/callbacks/gan/schedulers/BaseLrScheduler.py
lb_pidsim_train/callbacks/gan/schedulers/ExpLrScheduler.py
lb_pidsim_train/callbacks/gan/schedulers/PowLrScheduler.py
lb_pidsim_train/callbacks/gan/schedulers/__init__.py
lb_pidsim_train/layers/AddRandomFeatures.py
lb_pidsim_train/layers/Triangular.py
lb_pidsim_train/layers/__init__.py
lb_pidsim_train/metrics/JS_div.py
lb_pidsim_train/metrics/KL_div.py
lb_pidsim_train/metrics/KS_test.py
lb_pidsim_train/metrics/Variance.py
lb_pidsim_train/metrics/__init__.py
lb_pidsim_train/metrics/chi2_test.py
lb_pidsim_train/preprocessing/LbColTransformer.py
lb_pidsim_train/preprocessing/WeightedQuantileTransformer.py
lb_pidsim_train/preprocessing/__init__.py
lb_pidsim_train/trainers/BaseTrainer.py
lb_pidsim_train/trainers/DataHandler.py
lb_pidsim_train/trainers/GanTrainer.py
lb_pidsim_train/trainers/NormFlowTrainer.py
lb_pidsim_train/trainers/ScikitClassifier.py
lb_pidsim_train/trainers/ScikitTrainer.py
lb_pidsim_train/trainers/TensorTrainer.py
lb_pidsim_train/trainers/__init__.py
lb_pidsim_train/utils/ParamHandler.py
lb_pidsim_train/utils/__init__.py
lb_pidsim_train/utils/argparser.py
lb_pidsim_train/utils/data_from_trees.py
lb_pidsim_train/utils/getBinCounts.py
lb_pidsim_train-0.2.1.dist-info/LICENSE
lb_pidsim_train-0.2.1.dist-info/METADATA
lb_pidsim_train-0.2.1.dist-info/WHEEL
lb_pidsim_train-0.2.1.dist-info/top_level.txt
lb_pidsim_train-0.2.1.dist-info/RECORD
