Metadata-Version: 2.1
Name: lb-pidsim-train
Version: 0.2.1
Summary: Training pipeline for the parameterization of the LHCb PID system
Home-page: https://github.com/mbarbetti/lb-pidsim-train
Author: Matteo Barbetti
Author-email: matteo.barbetti@fi.infn.it
Maintainer: Matteo Barbetti, Lucio Anderlini
Maintainer-email: matteo.barbetti@fi.infn.it, lucio.anderlini@fi.infn.it
License: GPLv3
Platform: UNKNOWN
Classifier: Development Status :: 4 - Beta
Classifier: Intended Audience :: Science/Research
Classifier: Intended Audience :: Developers
Classifier: License :: OSI Approved :: GNU General Public License v3 (GPLv3)
Classifier: Programming Language :: Python :: 3
Classifier: Programming Language :: Python :: 3.7
Classifier: Programming Language :: Python :: 3.8
Classifier: Programming Language :: Python :: 3.9
Classifier: Programming Language :: Python :: 3 :: Only
Classifier: Topic :: Scientific/Engineering
Classifier: Topic :: Scientific/Engineering :: Physics
Classifier: Topic :: Scientific/Engineering :: Artificial Intelligence
Classifier: Topic :: Software Development
Classifier: Topic :: Software Development :: Libraries
Classifier: Topic :: Software Development :: Libraries :: Python Modules
Requires-Python: >=3.7, <3.10
License-File: LICENSE
Requires-Dist: tensorflow (>=2.5)
Requires-Dist: scikit-learn (>=1.0)
Requires-Dist: uproot (>=4.0)
Requires-Dist: matplotlib (>=3.4)
Requires-Dist: html-reports (>=0.2)
Requires-Dist: scikinC (>=0.2.6)
Requires-Dist: numpy
Requires-Dist: pandas
Requires-Dist: hopaas-client
